certbot_dns_e2econfig/__init__.py
certbot_dns_e2econfig/dns_e2econfig.py
certbot_dns_e2econfig-0.4.9.dist-info/LICENSE.txt
certbot_dns_e2econfig-0.4.9.dist-info/METADATA
certbot_dns_e2econfig-0.4.9.dist-info/WHEEL
certbot_dns_e2econfig-0.4.9.dist-info/entry_points.txt
certbot_dns_e2econfig-0.4.9.dist-info/top_level.txt
certbot_dns_e2econfig-0.4.9.dist-info/RECORD
